top_axi_iic_spi/top_axi_iic_spi.srcs/sources_1/new/axi_lite_slave.v
`timescale 1ns / 1ps

module axi_lite_slave(
    input  wire        clk,
    input  wire        rst_n,

    input  wire        awvalid,
    output wire        awready,
    input  wire [31:0] awaddr,

    input  wire        wvalid,
    output wire        wready,
    input  wire [31:0] wdata,

    output reg         bvalid,
    input  wire        bready,
    output reg  [1:0]  bresp,

    input  wire        arvalid,
    output wire        arready,
    input  wire [31:0] araddr,

    output reg         rvalid,
    input  wire        rready,
    output reg  [31:0] rdata,
    output reg  [1:0]  rresp,

    output reg         reg_wr_en,
    output reg         reg_rd_en,
    output reg  [1:0]  reg_addr,
    output reg  [31:0] reg_wdata,
    input  wire [31:0] reg_rdata
    );

    localparam W_COLLECT = 2'd0;
    localparam W_DO      = 2'd1;
    localparam W_RESP    = 2'd2;

    localparam R_IDLE = 2'd0;
    localparam R_REQ  = 2'd1;
    localparam R_WAIT = 2'd2;
    localparam R_RESP = 2'd3;

    reg [1:0]  wstate;
    reg [1:0]  rstate;
    reg        aw_seen;
    reg        w_seen;
    reg [31:0] awaddr_latched;
    reg [31:0] wdata_latched;

    wire aw_fire = awvalid && awready;
    wire w_fire  = wvalid  && wready;
    wire have_aw = aw_seen || aw_fire;
    wire have_w  = w_seen  || w_fire;

    // This simple slave serializes read and write accesses, matching the single-register-port design.
    assign awready = (wstate == W_COLLECT) && !aw_seen && (rstate == R_IDLE);
    assign wready  = (wstate == W_COLLECT) && !w_seen  && (rstate == R_IDLE);
    assign arready = (rstate == R_IDLE) && (wstate == W_COLLECT) &&
                     !aw_seen && !w_seen && !awvalid && !wvalid;

    always @(posedge clk or negedge rst_n) begin
        if (!rst_n) begin
            wstate         <= W_COLLECT;
            rstate         <= R_IDLE;
            aw_seen        <= 1'b0;
            w_seen         <= 1'b0;
            awaddr_latched <= 32'd0;
            wdata_latched  <= 32'd0;
            bvalid         <= 1'b0;
            bresp          <= 2'b00;
            rvalid         <= 1'b0;
            rdata          <= 32'd0;
            rresp          <= 2'b00;
            reg_wr_en      <= 1'b0;
            reg_rd_en      <= 1'b0;
            reg_addr       <= 2'd0;
            reg_wdata      <= 32'd0;
        end else begin
            reg_wr_en <= 1'b0;
            reg_rd_en <= 1'b0;

            case (wstate)
                W_COLLECT: begin
                    // AXI write address and data may arrive in different cycles; latch both before writing.
                    if (aw_fire) begin
                        aw_seen        <= 1'b1;
                        awaddr_latched <= awaddr;
                    end
                    if (w_fire) begin
                        w_seen        <= 1'b1;
                        wdata_latched <= wdata;
                    end

                    if (have_aw && have_w) begin
                        reg_addr  <= aw_seen ? awaddr_latched[3:2] : awaddr[3:2];
                        reg_wdata <= w_seen  ? wdata_latched       : wdata;
                        aw_seen   <= 1'b0;
                        w_seen    <= 1'b0;
                        wstate    <= W_DO;
                    end
                end

                W_DO: begin
                    reg_wr_en <= 1'b1;
                    bvalid    <= 1'b1;
                    bresp     <= 2'b00;
                    wstate    <= W_RESP;
                end

                W_RESP: begin
                    if (bvalid && bready) begin
                        bvalid <= 1'b0;
                        wstate <= W_COLLECT;
                    end
                end

                default: begin
                    wstate <= W_COLLECT;
                end
            endcase

            case (rstate)
                R_IDLE: begin
                    if (arvalid && arready) begin
                        reg_addr <= araddr[3:2];
                        rstate   <= R_REQ;
                    end
                end

                R_REQ: begin
                    // One-cycle read pulse; reg_file returns data on reg_rdata for R_WAIT.
                    reg_rd_en <= 1'b1;
                    rstate    <= R_WAIT;
                end

                R_WAIT: begin
                    rdata  <= reg_rdata;
                    rresp  <= 2'b00;
                    rvalid <= 1'b1;
                    rstate <= R_RESP;
                end

                R_RESP: begin
                    if (rvalid && rready) begin
                        rvalid <= 1'b0;
                        rstate <= R_IDLE;
                    end
                end

                default: begin
                    rstate <= R_IDLE;
                end
            endcase
        end
    end

endmodule

top_axi_iic_spi/top_axi_iic_spi.srcs/sim_1/new/tb_axi_lite_slave.v
`timescale 1ns / 1ps

module tb_axi_lite_slave;

    reg         clk = 1'b0;
    reg         rst_n = 1'b1;
    reg         awvalid = 1'b0;
    wire        awready;
    reg  [31:0] awaddr = 32'd0;
    reg         wvalid = 1'b0;
    wire        wready;
    reg  [31:0] wdata = 32'd0;
    wire        bvalid;
    reg         bready = 1'b0;
    wire [1:0]  bresp;
    reg         arvalid = 1'b0;
    wire        arready;
    reg  [31:0] araddr = 32'd0;
    wire        rvalid;
    reg         rready = 1'b0;
    wire [31:0] rdata;
    wire [1:0]  rresp;
    wire        reg_wr_en;
    wire        reg_rd_en;
    wire [1:0]  reg_addr;
    wire [31:0] reg_wdata;
    reg  [31:0] reg_rdata = 32'd0;

    reg [31:0] mem [0:3];
    reg [31:0] read_back = 32'd0;
    integer    errors = 0;

    axi_lite_slave dut (
        .clk       (clk),
        .rst_n     (rst_n),
        .awvalid   (awvalid),
        .awready   (awready),
        .awaddr    (awaddr),
        .wvalid    (wvalid),
        .wready    (wready),
        .wdata     (wdata),
        .bvalid    (bvalid),
        .bready    (bready),
        .bresp     (bresp),
        .arvalid   (arvalid),
        .arready   (arready),
        .araddr    (araddr),
        .rvalid    (rvalid),
        .rready    (rready),
        .rdata     (rdata),
        .rresp     (rresp),
        .reg_wr_en (reg_wr_en),
        .reg_rd_en (reg_rd_en),
        .reg_addr  (reg_addr),
        .reg_wdata (reg_wdata),
        .reg_rdata (reg_rdata)
    );

    initial forever #5 clk = ~clk;

    always @(*) begin
        case (reg_addr)
            2'd0: reg_rdata = mem[0];
            2'd1: reg_rdata = mem[1];
            2'd2: reg_rdata = mem[2];
            2'd3: reg_rdata = mem[3];
            default: reg_rdata = 32'd0;
        endcase
    end

    always @(posedge clk) begin
        if (reg_wr_en) mem[reg_addr] <= reg_wdata; // Register write pulse from AXI slave.
    end

    task fail;
        input [1023:0] msg;
        begin
            errors = errors + 1;
            $display("[%0t] FAIL: %0s", $time, msg);
        end
    endtask

    task axi_write;
        input [31:0] addr;
        input [31:0] data;
        integer timeout;
        begin
            @(negedge clk);
            awaddr  = addr;
            wdata   = data;
            awvalid = 1'b1;
            wvalid  = 1'b1;
            bready  = 1'b0;

            timeout = 0;
            while (!(awready && wready)) begin
                @(negedge clk);
                timeout = timeout + 1;
                if (timeout > 100) begin
                    fail("AXI write handshake timeout");
                    disable axi_write;
                end
            end
            @(posedge clk);
            #1;
            awvalid = 1'b0;
            wvalid  = 1'b0;

            bready = 1'b1;
            timeout = 0;
            while (!bvalid) begin
                @(posedge clk);
                #1;
                timeout = timeout + 1;
                if (timeout > 100) begin
                    fail("AXI write response timeout");
                    disable axi_write;
                end
            end
            if (bresp != 2'b00) fail("AXI write response is not OKAY");
            @(posedge clk);
            #1;
            bready = 1'b0;
        end
    endtask

    task axi_read;
        input  [31:0] addr;
        output [31:0] data;
        integer timeout;
        begin
            @(negedge clk);
            araddr  = addr;
            arvalid = 1'b1;
            rready  = 1'b0;

            timeout = 0;
            while (!arready) begin
                @(negedge clk);
                timeout = timeout + 1;
                if (timeout > 100) begin
                    fail("AXI read address timeout");
                    disable axi_read;
                end
            end
            @(posedge clk);
            #1;
            arvalid = 1'b0;

            rready = 1'b1;
            timeout = 0;
            while (!rvalid) begin
                @(posedge clk);
                #1;
                timeout = timeout + 1;
                if (timeout > 100) begin
                    fail("AXI read data timeout");
                    disable axi_read;
                end
            end
            data = rdata;
            if (rresp != 2'b00) fail("AXI read response is not OKAY");
            @(posedge clk);
            #1;
            rready = 1'b0;
        end
    endtask

    initial begin
        $dumpfile("tb_axi_lite_slave.vcd");
        $dumpvars(0, tb_axi_lite_slave);

        errors = 0;
        mem[0] = 32'd0;
        mem[1] = 32'd0;
        mem[2] = 32'd0;
        mem[3] = 32'd0;
        rst_n = 1'b0; // Create a real negedge at time 0 for async reset.

        repeat (5) @(posedge clk);
        rst_n = 1'b1;
        repeat (2) @(posedge clk);

        axi_write(32'h0000_0004, 32'h1234_5678);
        if (mem[1] != 32'h1234_5678) fail("write pulse did not update register index 1");

        axi_read(32'h0000_0004, read_back);
        if (read_back != 32'h1234_5678) fail("read data mismatch at address 0x04");

        axi_write(32'h0000_000c, 32'ha5a5_5a5a);
        axi_read(32'h0000_000c, read_back);
        if (read_back != 32'ha5a5_5a5a) fail("read data mismatch at address 0x0c");

        repeat (5) @(posedge clk);
        if (errors == 0) $display("[%0t] PASS: tb_axi_lite_slave", $time);
        else             $display("[%0t] FAIL: tb_axi_lite_slave found %0d error(s)", $time, errors);
        $finish;
    end

endmodule

top_axi_iic_spi/top_axi_iic_spi.sim/sim_1/behav/xsim/tb_axi_lite_slave.vcd
$date
   Fri May 29 09:40:29 2026
$end
$version
  2021.2
$end
$timescale
  1ps
$end
$scope module tb_axi_lite_slave $end
$var reg 1 ! clk $end
$var reg 1 " rst_n $end
$var reg 1 # awvalid $end
$var wire 1 $ awready $end
$var reg 32 % awaddr [31:0] $end
$var reg 1 & wvalid $end
$var wire 1 ' wready $end
$var reg 32 ( wdata [31:0] $end
$var wire 1 ) bvalid $end
$var reg 1 * bready $end
$var wire 2 + bresp [1:0] $end
$var reg 1 , arvalid $end
$var wire 1 - arready $end
$var reg 32 . araddr [31:0] $end
$var wire 1 / rvalid $end
$var reg 1 0 rready $end
$var wire 32 1 rdata [31:0] $end
$var wire 2 2 rresp [1:0] $end
$var wire 1 3 reg_wr_en $end
$var wire 1 4 reg_rd_en $end
$var wire 2 5 reg_addr [1:0] $end
$var wire 32 6 reg_wdata [31:0] $end
$var reg 32 7 reg_rdata [31:0] $end
$var reg 32 8 read_back [31:0] $end
$var integer 32 9 errors [31:0] $end
$scope module dut $end
$var wire 1 : clk $end
$var wire 1 ; rst_n $end
$var wire 1 < awvalid $end
$var wire 1 $ awready $end
$var wire 32 = awaddr [31:0] $end
$var wire 1 > wvalid $end
$var wire 1 ' wready $end
$var wire 32 ? wdata [31:0] $end
$var reg 1 @ bvalid $end
$var wire 1 A bready $end
$var reg 2 B bresp [1:0] $end
$var wire 1 C arvalid $end
$var wire 1 - arready $end
$var wire 32 D araddr [31:0] $end
$var reg 1 E rvalid $end
$var wire 1 F rready $end
$var reg 32 G rdata [31:0] $end
$var reg 2 H rresp [1:0] $end
$var reg 1 I reg_wr_en $end
$var reg 1 J reg_rd_en $end
$var reg 2 K reg_addr [1:0] $end
$var reg 32 L reg_wdata [31:0] $end
$var wire 32 M reg_rdata [31:0] $end
$var reg 2 N wstate [1:0] $end
$var reg 2 O rstate [1:0] $end
$var reg 1 P aw_seen $end
$var reg 1 Q w_seen $end
$var reg 32 R awaddr_latched [31:0] $end
$var reg 32 S wdata_latched [31:0] $end
$var wire 1 T aw_fire $end
$var wire 1 U w_fire $end
$var wire 1 V have_aw $end
$var wire 1 W have_w $end
$upscope $end
$scope task fail $end
$var reg 1024 X msg [1023:0] $end
$upscope $end
$scope task axi_write $end
$var reg 32 Y addr [31:0] $end
$var reg 32 Z data [31:0] $end
$var integer 32 [ timeout [31:0] $end
$upscope $end
$scope task axi_read $end
$var reg 32 \ addr [31:0] $end
$var reg 32 ] data [31:0] $end
$var integer 32 ^ timeout [31:0] $end
$upscope $end
$upscope $end
$enddefinitions $end
#0
$dumpvars
0!
0"
0#
1$
b0 %
0&
1'
b0 (
0)
0*
b0 +
0,
1-
b0 .
0/
00
b0 1
b0 2
03
04
b0 5
b0 6
b0 7
b0 8
b0 9
0:
0;
0<
b0 =
0>
b0 ?
0@
0A
b0 B
0C
b0 D
0E
0F
b0 G
b0 H
0I
0J
b0 K
b0 L
b0 M
b0 N
b0 O
0P
0Q
b0 R
b0 S
0T
0U
0V
0W
bx X
bx Y
bx Z
bx [
bx \
bx ]
bx ^
$end
#5000
1!
1:
#10000
0!
0:
#15000
1!
1:
#20000
0!
0:
#25000
1!
1:
#30000
0!
0:
#35000
1!
1:
#40000
0!
0:
#45000
1!
1"
1:
1;
#50000
0!
0:
#55000
1!
1:
#60000
0!
0:
#65000
1!
1:
b100 Y
b10010001101000101011001111000 Z
#70000
0!
1#
b100 %
1&
b10010001101000101011001111000 (
0-
0:
1<
b100 =
1>
b10010001101000101011001111000 ?
1T
1U
1V
1W
b0 [
#75000
1!
0$
0'
b1 5
b10010001101000101011001111000 6
b0 7
1:
b1 K
b10010001101000101011001111000 L
b1 N
0P
0Q
b100 R
b10010001101000101011001111000 S
0T
0U
0V
0W
#76000
0#
0&
1*
0<
0>
1A
0T
0U
#80000
0!
0:
#85000
1!
0$
0'
1)
13
1:
1@
1I
b10 N
#86000
b1 [
#90000
0!
0:
#95000
1!
1$
1'
0)
1-
03
b10010001101000101011001111000 7
1:
0@
0I
b10010001101000101011001111000 M
b0 N
0T
0U
#96000
0*
0A
b100 \
#100000
0!
1,
b100 .
0:
1C
b100 D
b0 ^
#105000
1!
0$
0'
0-
1:
b1 O
0T
0U
#106000
0,
10
0C
1F
#110000
0!
0:
#115000
1!
0$
0'
14
1:
1J
b10 O
#116000
b1 ^
#120000
0!
0:
#125000
1!
0$
0'
1/
b10010001101000101011001111000 1
04
1:
1E
b10010001101000101011001111000 G
0J
b11 O
#126000
b10010001101000101011001111000 ]
b10 ^
#130000
0!
0:
#135000
1!
1$
1'
1-
0/
1:
0E
b0 O
0T
0U
#136000
00
b10010001101000101011001111000 8
0F
b1100 Y
b10100101101001010101101001011010 Z
#140000
0!
1#
b1100 %
1&
b10100101101001010101101001011010 (
0-
0:
1<
b1100 =
1>
b10100101101001010101101001011010 ?
1T
1U
1V
1W
b0 [
#145000
1!
0$
0'
b11 5
b10100101101001010101101001011010 6
b0 7
1:
b11 K
b10100101101001010101101001011010 L
b0 M
b1 N
0P
0Q
b1100 R
b10100101101001010101101001011010 S
0T
0U
0V
0W
#146000
0#
0&
1*
0<
0>
1A
0T
0U
#150000
0!
0:
#155000
1!
0$
0'
1)
13
1:
1@
1I
b10 N
#156000
b1 [
#160000
0!
0:
#165000
1!
1$
1'
0)
1-
03
b10100101101001010101101001011010 7
1:
0@
0I
b10100101101001010101101001011010 M
b0 N
0T
0U
#166000
0*
0A
b1100 \
#170000
0!
1,
b1100 .
0:
1C
b1100 D
b0 ^
#175000
1!
0$
0'
0-
1:
b1 O
0T
0U
#176000
0,
10
0C
1F
#180000
0!
0:
#185000
1!
0$
0'
14
1:
1J
b10 O
#186000
b1 ^
#190000
0!
0:
#195000
1!
0$
0'
1/
b10100101101001010101101001011010 1
04
1:
1E
b10100101101001010101101001011010 G
0J
b11 O
#196000
b10100101101001010101101001011010 ]
b10 ^
#200000
0!
0:
#205000
1!
1$
1'
1-
0/
1:
0E
b0 O
0T
0U
#206000
00
b10100101101001010101101001011010 8
0F
