top_axi_iic_spi/top_axi_iic_spi.srcs/sources_1/new/reg_file.v
`timescale 1ns / 1ps

module reg_file(
    input  wire        clk,
    input  wire        rst_n,

    input  wire        reg_wr_en,
    input  wire        reg_rd_en,
    input  wire [1:0]  reg_addr,
    input  wire [31:0] reg_wdata,
    output reg  [31:0] reg_rdata,

    output reg         iic_start,
    output wire [7:0]  iic_dev_addr,
    output wire [7:0]  iic_data,
    input  wire        iic_done,

    output reg         spi_start,
    output wire [7:0]  spi_data,
    input  wire        spi_done,

    output reg         iic_busy,
    output reg         iic_done_flag,
    output reg         spi_busy,
    output reg         spi_done_flag
    );

    localparam REG_CTRL    = 2'd0;
    localparam REG_IICDATA = 2'd1;
    localparam REG_SPIDATA = 2'd2;
    localparam REG_STATUS  = 2'd3;

    reg [31:0] iic_data_reg;
    reg [31:0] spi_data_reg;

    assign iic_dev_addr = iic_data_reg[15:8];
    assign iic_data     = iic_data_reg[7:0];
    assign spi_data     = spi_data_reg[7:0];

    always @(posedge clk or negedge rst_n) begin
        if (!rst_n) begin
            iic_data_reg  <= 32'd0;
            spi_data_reg  <= 32'd0;
            reg_rdata     <= 32'd0;
            iic_start     <= 1'b0;
            spi_start     <= 1'b0;
            iic_busy      <= 1'b0;
            iic_done_flag <= 1'b0;
            spi_busy      <= 1'b0;
            spi_done_flag <= 1'b0;
        end else begin
            iic_start <= 1'b0;
            spi_start <= 1'b0;

            if (iic_done) begin
                iic_busy      <= 1'b0;
                iic_done_flag <= 1'b1;
            end

            if (spi_done) begin
                spi_busy      <= 1'b0;
                spi_done_flag <= 1'b1;
            end

            if (reg_wr_en) begin
                case (reg_addr)
                    REG_CTRL: begin
                        // CTRL writes generate one-cycle triggers; busy blocks repeated starts.
                        if (reg_wdata[0] && !iic_busy) begin
                            iic_start     <= 1'b1;
                            iic_busy      <= 1'b1;
                            iic_done_flag <= 1'b0;
                        end
                        if (reg_wdata[1] && !spi_busy) begin
                            spi_start     <= 1'b1;
                            spi_busy      <= 1'b1;
                            spi_done_flag <= 1'b0;
                        end
                    end

                    REG_IICDATA: begin
                        iic_data_reg <= reg_wdata;
                    end

                    REG_SPIDATA: begin
                        spi_data_reg <= reg_wdata;
                    end

                    default: begin
                    end
                endcase
            end

            if (reg_rd_en) begin
                case (reg_addr)
                    REG_CTRL: begin
                        reg_rdata <= 32'd0;
                    end

                    REG_IICDATA: begin
                        reg_rdata <= iic_data_reg;
                    end

                    REG_SPIDATA: begin
                        reg_rdata <= spi_data_reg;
                    end

                    REG_STATUS: begin
                        // STATUS: bit0 iic_busy, bit1 iic_done, bit2 spi_busy, bit3 spi_done.
                        reg_rdata <= {
                            28'd0,
                            (spi_done_flag || spi_done),
                            (spi_busy && !spi_done),
                            (iic_done_flag || iic_done),
                            (iic_busy && !iic_done)
                        };
                        iic_done_flag <= 1'b0;
                        spi_done_flag <= 1'b0;
                    end

                    default: begin
                        reg_rdata <= 32'd0;
                    end
                endcase
            end
        end
    end

endmodule

top_axi_iic_spi/top_axi_iic_spi.srcs/sim_1/new/tb_reg_file.v
`timescale 1ns / 1ps

module tb_reg_file;

    reg         clk = 1'b0;
    reg         rst_n = 1'b1;
    reg         reg_wr_en = 1'b0;
    reg         reg_rd_en = 1'b0;
    reg  [1:0]  reg_addr = 2'd0;
    reg  [31:0] reg_wdata = 32'd0;
    wire [31:0] reg_rdata;
    wire        iic_start;
    wire [7:0]  iic_dev_addr;
    wire [7:0]  iic_data;
    reg         iic_done = 1'b0;
    wire        spi_start;
    wire [7:0]  spi_data;
    reg         spi_done = 1'b0;
    wire        iic_busy;
    wire        iic_done_flag;
    wire        spi_busy;
    wire        spi_done_flag;

    reg [31:0] status = 32'd0;
    integer    errors = 0;

    reg_file dut (
        .clk           (clk),
        .rst_n         (rst_n),
        .reg_wr_en     (reg_wr_en),
        .reg_rd_en     (reg_rd_en),
        .reg_addr      (reg_addr),
        .reg_wdata     (reg_wdata),
        .reg_rdata     (reg_rdata),
        .iic_start     (iic_start),
        .iic_dev_addr  (iic_dev_addr),
        .iic_data      (iic_data),
        .iic_done      (iic_done),
        .spi_start     (spi_start),
        .spi_data      (spi_data),
        .spi_done      (spi_done),
        .iic_busy      (iic_busy),
        .iic_done_flag (iic_done_flag),
        .spi_busy      (spi_busy),
        .spi_done_flag (spi_done_flag)
    );

    initial forever #5 clk = ~clk;

    task fail;
        input [1023:0] msg;
        begin
            errors = errors + 1;
            $display("[%0t] FAIL: %0s", $time, msg);
        end
    endtask

    task reg_write;
        input [1:0]  addr;
        input [31:0] data;
        begin
            @(negedge clk);
            reg_addr   = addr;
            reg_wdata  = data;
            reg_wr_en  = 1'b1;
            @(posedge clk);
            #1;
            @(negedge clk);
            reg_wr_en = 1'b0;
        end
    endtask

    task reg_read;
        input  [1:0]  addr;
        output [31:0] data;
        begin
            @(negedge clk);
            reg_addr  = addr;
            reg_rd_en = 1'b1;
            @(posedge clk);
            #1;
            data = reg_rdata;
            @(negedge clk);
            reg_rd_en = 1'b0;
        end
    endtask

    task pulse_iic_done;
        begin
            @(negedge clk);
            iic_done = 1'b1;
            @(posedge clk);
            #1;
            iic_done = 1'b0;
        end
    endtask

    task pulse_spi_done;
        begin
            @(negedge clk);
            spi_done = 1'b1;
            @(posedge clk);
            #1;
            spi_done = 1'b0;
        end
    endtask

    initial begin
        $dumpfile("tb_reg_file.vcd");
        $dumpvars(0, tb_reg_file);

        errors = 0;
        rst_n = 1'b0; // Create a real negedge at time 0 for async reset.

        repeat (5) @(posedge clk);
        rst_n = 1'b1;
        repeat (2) @(posedge clk);

        reg_write(2'd1, 32'h0000_50a5); // IIC_DATA register.
        if (iic_dev_addr != 8'h50) fail("IIC device address decode mismatch");
        if (iic_data != 8'ha5)     fail("IIC data decode mismatch");

        reg_write(2'd0, 32'h0000_0001); // CTRL bit0 is a one-cycle IIC trigger.
        if (!iic_start) fail("IIC start pulse missing");
        if (!iic_busy)  fail("IIC busy was not set by start");
        @(posedge clk);
        #1;
        if (iic_start) fail("IIC start pulse stayed high too long");

        pulse_iic_done();
        if (iic_busy)       fail("IIC busy did not clear on done");
        if (!iic_done_flag) fail("IIC done flag did not set");
        reg_read(2'd3, status);
        if (status[1] != 1'b1) fail("STATUS bit1 did not report iic_done");
        reg_read(2'd3, status);
        if (status[1] != 1'b0) fail("STATUS read did not clear iic_done");

        reg_write(2'd2, 32'h0000_005c); // SPI_DATA register.
        if (spi_data != 8'h5c) fail("SPI data decode mismatch");

        reg_write(2'd0, 32'h0000_0002); // CTRL bit1 is a one-cycle SPI trigger.
        if (!spi_start) fail("SPI start pulse missing");
        if (!spi_busy)  fail("SPI busy was not set by start");
        @(posedge clk);
        #1;
        if (spi_start) fail("SPI start pulse stayed high too long");

        pulse_spi_done();
        if (spi_busy)       fail("SPI busy did not clear on done");
        if (!spi_done_flag) fail("SPI done flag did not set");
        reg_read(2'd3, status);
        if (status[3] != 1'b1) fail("STATUS bit3 did not report spi_done");
        reg_read(2'd3, status);
        if (status[3] != 1'b0) fail("STATUS read did not clear spi_done");

        repeat (5) @(posedge clk);
        if (errors == 0) $display("[%0t] PASS: tb_reg_file", $time);
        else             $display("[%0t] FAIL: tb_reg_file found %0d error(s)", $time, errors);
        $finish;
    end

endmodule

top_axi_iic_spi/top_axi_iic_spi.sim/sim_1/behav/xsim/tb_reg_file.vcd
$date
   Fri May 29 09:35:06 2026
$end
$version
  2021.2
$end
$timescale
  1ps
$end
$scope module tb_reg_file $end
$var reg 1 ! clk $end
$var reg 1 " rst_n $end
$var reg 1 # reg_wr_en $end
$var reg 1 $ reg_rd_en $end
$var reg 2 % reg_addr [1:0] $end
$var reg 32 & reg_wdata [31:0] $end
$var wire 32 ' reg_rdata [31:0] $end
$var wire 1 ( iic_start $end
$var wire 8 ) iic_dev_addr [7:0] $end
$var wire 8 * iic_data [7:0] $end
$var reg 1 + iic_done $end
$var wire 1 , spi_start $end
$var wire 8 - spi_data [7:0] $end
$var reg 1 . spi_done $end
$var wire 1 / iic_busy $end
$var wire 1 0 iic_done_flag $end
$var wire 1 1 spi_busy $end
$var wire 1 2 spi_done_flag $end
$var reg 32 3 status [31:0] $end
$var integer 32 4 errors [31:0] $end
$scope module dut $end
$var wire 1 5 clk $end
$var wire 1 6 rst_n $end
$var wire 1 7 reg_wr_en $end
$var wire 1 8 reg_rd_en $end
$var wire 2 9 reg_addr [1:0] $end
$var wire 32 : reg_wdata [31:0] $end
$var reg 32 ; reg_rdata [31:0] $end
$var reg 1 < iic_start $end
$var wire 8 ) iic_dev_addr [7:0] $end
$var wire 8 * iic_data [7:0] $end
$var wire 1 = iic_done $end
$var reg 1 > spi_start $end
$var wire 8 - spi_data [7:0] $end
$var wire 1 ? spi_done $end
$var reg 1 @ iic_busy $end
$var reg 1 A iic_done_flag $end
$var reg 1 B spi_busy $end
$var reg 1 C spi_done_flag $end
$var reg 32 D iic_data_reg [31:0] $end
$var reg 32 E spi_data_reg [31:0] $end
$upscope $end
$scope task fail $end
$var reg 1024 F msg [1023:0] $end
$upscope $end
$scope task reg_write $end
$var reg 2 G addr [1:0] $end
$var reg 32 H data [31:0] $end
$upscope $end
$scope task reg_read $end
$var reg 2 I addr [1:0] $end
$var reg 32 J data [31:0] $end
$upscope $end
$scope task pulse_iic_done $end
$upscope $end
$scope task pulse_spi_done $end
$upscope $end
$upscope $end
$enddefinitions $end
#0
$dumpvars
0!
0"
0#
0$
b0 %
b0 &
b0 '
0(
b0 )
b0 *
0+
0,
b0 -
0.
0/
00
01
02
b0 3
b0 4
05
06
07
08
b0 9
b0 :
b0 ;
0<
0=
0>
0?
0@
0A
0B
0C
b0 D
b0 E
bx F
bx G
bx H
bx I
bx J
$end
#5000
1!
15
#10000
0!
05
#15000
1!
15
#20000
0!
05
#25000
1!
15
#30000
0!
05
#35000
1!
15
#40000
0!
05
#45000
1!
1"
15
16
#50000
0!
05
#55000
1!
15
#60000
0!
05
#65000
1!
15
b1 G
b101000010100101 H
#70000
0!
1#
b1 %
b101000010100101 &
05
17
b1 9
b101000010100101 :
#75000
1!
b1010000 )
b10100101 *
15
b101000010100101 D
#80000
0!
0#
05
07
b0 G
b1 H
#85000
1!
15
#90000
0!
1#
b0 %
b1 &
05
17
b0 9
b1 :
#95000
1!
1(
1/
15
1<
1@
#100000
0!
0#
05
07
#105000
1!
0(
15
0<
#110000
0!
1+
05
1=
#115000
1!
0/
10
15
0@
1A
#116000
0+
0=
b11 I
#120000
0!
1$
b11 %
05
18
b11 9
#125000
1!
b10 '
00
15
b10 ;
0A
#126000
b10 J
#130000
0!
0$
b10 3
05
08
#135000
1!
15
#140000
0!
1$
b11 %
05
18
#145000
1!
b0 '
15
b0 ;
#146000
b0 J
#150000
0!
0$
b0 3
05
08
b10 G
b1011100 H
#155000
1!
15
#160000
0!
1#
b10 %
b1011100 &
05
17
b10 9
b1011100 :
#165000
1!
b1011100 -
15
b1011100 E
#170000
0!
0#
05
07
b0 G
b10 H
#175000
1!
15
#180000
0!
1#
b0 %
b10 &
05
17
b0 9
b10 :
#185000
1!
1,
11
15
1>
1B
#190000
0!
0#
05
07
#195000
1!
0,
15
0>
#200000
0!
1.
05
1?
#205000
1!
01
12
15
0B
1C
#206000
0.
0?
#210000
0!
1$
b11 %
05
18
b11 9
#215000
1!
b1000 '
02
15
b1000 ;
0C
#216000
b1000 J
#220000
0!
0$
b1000 3
05
08
#225000
1!
15
#230000
0!
1$
b11 %
05
18
#235000
1!
b0 '
15
b0 ;
#236000
b0 J
#240000
0!
0$
b0 3
05
08
