top_axi_iic_spi/top_axi_iic_spi.srcs/sources_1/new/axi_lite_slave.v
`timescale 1ns / 1ps

module axi_lite_slave(
    input  wire        clk,
    input  wire        rst_n,

    input  wire        awvalid,
    output wire        awready,
    input  wire [31:0] awaddr,

    input  wire        wvalid,
    output wire        wready,
    input  wire [31:0] wdata,

    output reg         bvalid,
    input  wire        bready,
    output reg  [1:0]  bresp,

    input  wire        arvalid,
    output wire        arready,
    input  wire [31:0] araddr,

    output reg         rvalid,
    input  wire        rready,
    output reg  [31:0] rdata,
    output reg  [1:0]  rresp,

    output reg         reg_wr_en,
    output reg         reg_rd_en,
    output reg  [1:0]  reg_addr,
    output reg  [31:0] reg_wdata,
    input  wire [31:0] reg_rdata
    );

    localparam W_COLLECT = 2'd0;
    localparam W_DO      = 2'd1;
    localparam W_RESP    = 2'd2;

    localparam R_IDLE = 2'd0;
    localparam R_REQ  = 2'd1;
    localparam R_WAIT = 2'd2;
    localparam R_RESP = 2'd3;

    reg [1:0]  wstate;
    reg [1:0]  rstate;
    reg        aw_seen;
    reg        w_seen;
    reg [31:0] awaddr_latched;
    reg [31:0] wdata_latched;

    wire aw_fire = awvalid && awready;
    wire w_fire  = wvalid  && wready;
    wire have_aw = aw_seen || aw_fire;
    wire have_w  = w_seen  || w_fire;

    // This simple slave serializes read and write accesses, matching the single-register-port design.
    assign awready = (wstate == W_COLLECT) && !aw_seen && (rstate == R_IDLE);
    assign wready  = (wstate == W_COLLECT) && !w_seen  && (rstate == R_IDLE);
    assign arready = (rstate == R_IDLE) && (wstate == W_COLLECT) &&
                     !aw_seen && !w_seen && !awvalid && !wvalid;

    always @(posedge clk or negedge rst_n) begin
        if (!rst_n) begin
            wstate         <= W_COLLECT;
            rstate         <= R_IDLE;
            aw_seen        <= 1'b0;
            w_seen         <= 1'b0;
            awaddr_latched <= 32'd0;
            wdata_latched  <= 32'd0;
            bvalid         <= 1'b0;
            bresp          <= 2'b00;
            rvalid         <= 1'b0;
            rdata          <= 32'd0;
            rresp          <= 2'b00;
            reg_wr_en      <= 1'b0;
            reg_rd_en      <= 1'b0;
            reg_addr       <= 2'd0;
            reg_wdata      <= 32'd0;
        end else begin
            reg_wr_en <= 1'b0;
            reg_rd_en <= 1'b0;

            case (wstate)
                W_COLLECT: begin
                    // AXI write address and data may arrive in different cycles; latch both before writing.
                    if (aw_fire) begin
                        aw_seen        <= 1'b1;
                        awaddr_latched <= awaddr;
                    end
                    if (w_fire) begin
                        w_seen        <= 1'b1;
                        wdata_latched <= wdata;
                    end

                    if (have_aw && have_w) begin
                        reg_addr  <= aw_seen ? awaddr_latched[3:2] : awaddr[3:2];
                        reg_wdata <= w_seen  ? wdata_latched       : wdata;
                        aw_seen   <= 1'b0;
                        w_seen    <= 1'b0;
                        wstate    <= W_DO;
                    end
                end

                W_DO: begin
                    reg_wr_en <= 1'b1;
                    bvalid    <= 1'b1;
                    bresp     <= 2'b00;
                    wstate    <= W_RESP;
                end

                W_RESP: begin
                    if (bvalid && bready) begin
                        bvalid <= 1'b0;
                        wstate <= W_COLLECT;
                    end
                end

                default: begin
                    wstate <= W_COLLECT;
                end
            endcase

            case (rstate)
                R_IDLE: begin
                    if (arvalid && arready) begin
                        reg_addr <= araddr[3:2];
                        rstate   <= R_REQ;
                    end
                end

                R_REQ: begin
                    // One-cycle read pulse; reg_file returns data on reg_rdata for R_WAIT.
                    reg_rd_en <= 1'b1;
                    rstate    <= R_WAIT;
                end

                R_WAIT: begin
                    rdata  <= reg_rdata;
                    rresp  <= 2'b00;
                    rvalid <= 1'b1;
                    rstate <= R_RESP;
                end

                R_RESP: begin
                    if (rvalid && rready) begin
                        rvalid <= 1'b0;
                        rstate <= R_IDLE;
                    end
                end

                default: begin
                    rstate <= R_IDLE;
                end
            endcase
        end
    end

endmodule

top_axi_iic_spi/top_axi_iic_spi.srcs/sim_1/new/tb_axi_lite_slave.v
`timescale 1ns / 1ps

module tb_axi_lite_slave;

    reg         clk = 1'b0;
    reg         rst_n = 1'b1;
    reg         awvalid = 1'b0;
    wire        awready;
    reg  [31:0] awaddr = 32'd0;
    reg         wvalid = 1'b0;
    wire        wready;
    reg  [31:0] wdata = 32'd0;
    wire        bvalid;
    reg         bready = 1'b0;
    wire [1:0]  bresp;
    reg         arvalid = 1'b0;
    wire        arready;
    reg  [31:0] araddr = 32'd0;
    wire        rvalid;
    reg         rready = 1'b0;
    wire [31:0] rdata;
    wire [1:0]  rresp;
    wire        reg_wr_en;
    wire        reg_rd_en;
    wire [1:0]  reg_addr;
    wire [31:0] reg_wdata;
    reg  [31:0] reg_rdata = 32'd0;

    reg [31:0] mem [0:3];
    reg [31:0] read_back = 32'd0;
    integer    errors = 0;

    axi_lite_slave dut (
        .clk       (clk),
        .rst_n     (rst_n),
        .awvalid   (awvalid),
        .awready   (awready),
        .awaddr    (awaddr),
        .wvalid    (wvalid),
        .wready    (wready),
        .wdata     (wdata),
        .bvalid    (bvalid),
        .bready    (bready),
        .bresp     (bresp),
        .arvalid   (arvalid),
        .arready   (arready),
        .araddr    (araddr),
        .rvalid    (rvalid),
        .rready    (rready),
        .rdata     (rdata),
        .rresp     (rresp),
        .reg_wr_en (reg_wr_en),
        .reg_rd_en (reg_rd_en),
        .reg_addr  (reg_addr),
        .reg_wdata (reg_wdata),
        .reg_rdata (reg_rdata)
    );

    initial forever #5 clk = ~clk;

    always @(*) begin
        case (reg_addr)
            2'd0: reg_rdata = mem[0];
            2'd1: reg_rdata = mem[1];
            2'd2: reg_rdata = mem[2];
            2'd3: reg_rdata = mem[3];
            default: reg_rdata = 32'd0;
        endcase
    end

    always @(posedge clk) begin
        if (reg_wr_en) mem[reg_addr] <= reg_wdata; // Register write pulse from AXI slave.
    end

    task fail;
        input [1023:0] msg;
        begin
            errors = errors + 1;
            $display("[%0t] FAIL: %0s", $time, msg);
        end
    endtask

    task axi_write;
        input [31:0] addr;
        input [31:0] data;
        integer timeout;
        begin
            @(negedge clk);
            awaddr  = addr;
            wdata   = data;
            awvalid = 1'b1;
            wvalid  = 1'b1;
            bready  = 1'b0;

            timeout = 0;
            while (!(awready && wready)) begin
                @(negedge clk);
                timeout = timeout + 1;
                if (timeout > 100) begin
                    fail("AXI write handshake timeout");
                    disable axi_write;
                end
            end
            @(posedge clk);
            #1;
            awvalid = 1'b0;
            wvalid  = 1'b0;

            bready = 1'b1;
            timeout = 0;
            while (!bvalid) begin
                @(posedge clk);
                #1;
                timeout = timeout + 1;
                if (timeout > 100) begin
                    fail("AXI write response timeout");
                    disable axi_write;
                end
            end
            if (bresp != 2'b00) fail("AXI write response is not OKAY");
            @(posedge clk);
            #1;
            bready = 1'b0;
        end
    endtask

    task axi_read;
        input  [31:0] addr;
        output [31:0] data;
        integer timeout;
        begin
            @(negedge clk);
            araddr  = addr;
            arvalid = 1'b1;
            rready  = 1'b0;

            timeout = 0;
            while (!arready) begin
                @(negedge clk);
                timeout = timeout + 1;
                if (timeout > 100) begin
                    fail("AXI read address timeout");
                    disable axi_read;
                end
            end
            @(posedge clk);
            #1;
            arvalid = 1'b0;

            rready = 1'b1;
            timeout = 0;
            while (!rvalid) begin
                @(posedge clk);
                #1;
                timeout = timeout + 1;
                if (timeout > 100) begin
                    fail("AXI read data timeout");
                    disable axi_read;
                end
            end
            data = rdata;
            if (rresp != 2'b00) fail("AXI read response is not OKAY");
            @(posedge clk);
            #1;
            rready = 1'b0;
        end
    endtask

    initial begin
        $dumpfile("tb_axi_lite_slave.vcd");
        $dumpvars(0, tb_axi_lite_slave);

        errors = 0;
        mem[0] = 32'd0;
        mem[1] = 32'd0;
        mem[2] = 32'd0;
        mem[3] = 32'd0;
        rst_n = 1'b0; // Create a real negedge at time 0 for async reset.

        repeat (5) @(posedge clk);
        rst_n = 1'b1;
        repeat (2) @(posedge clk);

        axi_write(32'h0000_0004, 32'h1234_5678);
        if (mem[1] != 32'h1234_5678) fail("write pulse did not update register index 1");

        axi_read(32'h0000_0004, read_back);
        if (read_back != 32'h1234_5678) fail("read data mismatch at address 0x04");

        axi_write(32'h0000_000c, 32'ha5a5_5a5a);
        axi_read(32'h0000_000c, read_back);
        if (read_back != 32'ha5a5_5a5a) fail("read data mismatch at address 0x0c");

        repeat (5) @(posedge clk);
        if (errors == 0) $display("[%0t] PASS: tb_axi_lite_slave", $time);
        else             $display("[%0t] FAIL: tb_axi_lite_slave found %0d error(s)", $time, errors);
        $finish;
    end

endmodule

top_axi_iic_spi/tb_axi_lite_slave.vcd
$date
	Fri May 29 09:29:29 2026
$end
$version
	Icarus Verilog
$end
$timescale
	1ps
$end
$scope module tb_axi_lite_slave $end
$var wire 1 ! wready $end
$var wire 1 " rvalid $end
$var wire 2 # rresp [1:0] $end
$var wire 1 $ reg_wr_en $end
$var wire 32 % reg_wdata [31:0] $end
$var wire 1 & reg_rd_en $end
$var wire 2 ' reg_addr [1:0] $end
$var wire 32 ( rdata [31:0] $end
$var wire 1 ) bvalid $end
$var wire 2 * bresp [1:0] $end
$var wire 1 + awready $end
$var wire 1 , arready $end
$var reg 32 - araddr [31:0] $end
$var reg 1 . arvalid $end
$var reg 32 / awaddr [31:0] $end
$var reg 1 0 awvalid $end
$var reg 1 1 bready $end
$var reg 1 2 clk $end
$var reg 32 3 read_back [31:0] $end
$var reg 32 4 reg_rdata [31:0] $end
$var reg 1 5 rready $end
$var reg 1 6 rst_n $end
$var reg 32 7 wdata [31:0] $end
$var reg 1 8 wvalid $end
$var integer 32 9 errors [31:0] $end
$scope module dut $end
$var wire 32 : araddr [31:0] $end
$var wire 1 , arready $end
$var wire 1 . arvalid $end
$var wire 1 ; aw_fire $end
$var wire 32 < awaddr [31:0] $end
$var wire 1 + awready $end
$var wire 1 0 awvalid $end
$var wire 1 1 bready $end
$var wire 1 2 clk $end
$var wire 1 = have_aw $end
$var wire 1 > have_w $end
$var wire 32 ? reg_rdata [31:0] $end
$var wire 1 5 rready $end
$var wire 1 6 rst_n $end
$var wire 1 @ w_fire $end
$var wire 32 A wdata [31:0] $end
$var wire 1 ! wready $end
$var wire 1 8 wvalid $end
$var parameter 2 B R_IDLE $end
$var parameter 2 C R_REQ $end
$var parameter 2 D R_RESP $end
$var parameter 2 E R_WAIT $end
$var parameter 2 F W_COLLECT $end
$var parameter 2 G W_DO $end
$var parameter 2 H W_RESP $end
$var reg 1 I aw_seen $end
$var reg 32 J awaddr_latched [31:0] $end
$var reg 2 K bresp [1:0] $end
$var reg 1 ) bvalid $end
$var reg 32 L rdata [31:0] $end
$var reg 2 M reg_addr [1:0] $end
$var reg 1 & reg_rd_en $end
$var reg 32 N reg_wdata [31:0] $end
$var reg 1 $ reg_wr_en $end
$var reg 2 O rresp [1:0] $end
$var reg 2 P rstate [1:0] $end
$var reg 1 " rvalid $end
$var reg 1 Q w_seen $end
$var reg 32 R wdata_latched [31:0] $end
$var reg 2 S wstate [1:0] $end
$upscope $end
$scope task axi_read $end
$var reg 32 T addr [31:0] $end
$var reg 32 U data [31:0] $end
$var integer 32 V timeout [31:0] $end
$upscope $end
$scope task axi_write $end
$var reg 32 W addr [31:0] $end
$var reg 32 X data [31:0] $end
$var integer 32 Y timeout [31:0] $end
$upscope $end
$scope task fail $end
$var reg 1024 Z msg [1023:0] $end
$upscope $end
$upscope $end
$enddefinitions $end
$comment Show the parameter values. $end
$dumpall
b10 H
b1 G
b0 F
b10 E
b11 D
b1 C
b0 B
$end
#0
$dumpvars
bx Z
bx Y
bx X
bx W
bx V
bx U
bx T
b0 S
b0 R
0Q
b0 P
b0 O
b0 N
b0 M
b0 L
b0 K
b0 J
0I
b0 A
0@
b0 ?
0>
0=
b0 <
0;
b0 :
b0 9
08
b0 7
06
05
b0 4
b0 3
02
01
00
b0 /
0.
b0 -
1,
1+
b0 *
0)
b0 (
b0 '
0&
b0 %
0$
b0 #
0"
1!
$end
#5000
12
#10000
02
#15000
12
#20000
02
#25000
12
#30000
02
#35000
12
#40000
02
#45000
16
12
#50000
02
#55000
12
#60000
02
#65000
b10010001101000101011001111000 X
b100 W
12
#70000
1>
1=
1@
0,
1;
b0 Y
18
10
b10010001101000101011001111000 7
b10010001101000101011001111000 A
b100 /
b100 <
02
#75000
0>
0=
0@
0;
0!
0+
b1 S
b10010001101000101011001111000 %
b10010001101000101011001111000 N
b1 '
b1 M
b10010001101000101011001111000 R
0Q
b100 J
0I
12
#76000
11
08
00
#80000
02
#85000
b10 S
1)
1$
12
#86000
b1 Y
#90000
02
#95000
1,
1+
1!
b10010001101000101011001111000 4
b10010001101000101011001111000 ?
b0 S
0)
0$
12
#96000
b100 T
01
#100000
b0 V
1.
b100 -
b100 :
02
#105000
0,
0+
0!
b1 P
12
#106000
15
0.
#110000
02
#115000
b10 P
1&
12
#116000
b1 V
#120000
02
#125000
b11 P
1"
b10010001101000101011001111000 (
b10010001101000101011001111000 L
0&
12
#126000
b10010001101000101011001111000 U
b10 V
#130000
02
#135000
1,
1+
1!
b0 P
0"
12
#136000
b10100101101001010101101001011010 X
b1100 W
b10010001101000101011001111000 3
05
#140000
1>
1=
1@
0,
1;
b0 Y
18
10
b10100101101001010101101001011010 7
b10100101101001010101101001011010 A
b1100 /
b1100 <
02
#145000
0>
0=
0@
0;
0!
0+
b0 4
b0 ?
b1 S
b10100101101001010101101001011010 %
b10100101101001010101101001011010 N
b11 '
b11 M
b10100101101001010101101001011010 R
0Q
b1100 J
0I
12
#146000
11
08
00
#150000
02
#155000
b10 S
1)
1$
12
#156000
b1 Y
#160000
02
#165000
1,
1+
1!
b10100101101001010101101001011010 4
b10100101101001010101101001011010 ?
b0 S
0)
0$
12
#166000
b1100 T
01
#170000
b0 V
1.
b1100 -
b1100 :
02
#175000
0,
0+
0!
b1 P
12
#176000
15
0.
#180000
02
#185000
b10 P
1&
12
#186000
b1 V
#190000
02
#195000
b11 P
1"
b10100101101001010101101001011010 (
b10100101101001010101101001011010 L
0&
12
#196000
b10100101101001010101101001011010 U
b10 V
#200000
02
#205000
1,
1+
1!
b0 P
0"
12
#206000
b10100101101001010101101001011010 3
05
