top_axi_iic_spi/top_axi_iic_spi.srcs/sources_1/new/iic_master.v
`timescale 1ns / 1ps

module iic_master #(
    parameter integer CLK_DIV = 1000
    )(
    input  wire       clk,
    input  wire       rst_n,
    input  wire       iic_start,
    input  wire [7:0] dev_addr,
    input  wire [7:0] data,
    output reg        iic_done,
    output reg        scl,
    inout  wire       sda
    );

    localparam integer HALF_DIV = (CLK_DIV <= 2) ? 1 : (CLK_DIV / 2);

    localparam IDLE      = 3'd0;
    localparam START     = 3'd1;
    localparam SEND_ADDR = 3'd2;
    localparam WAIT_ACK1 = 3'd3;
    localparam SEND_DATA = 3'd4;
    localparam WAIT_ACK2 = 3'd5;
    localparam STOP      = 3'd6;

    reg [2:0]  state;
    reg [3:0]  bit_cnt;
    reg [7:0]  addr_shift;
    reg [7:0]  data_shift;
    reg [31:0] div_cnt;
    reg        phase;
    reg        sda_out;
    reg        sda_oe;
    reg        ack_sample;

    wire div_tick = (div_cnt == (HALF_DIV - 1));

    assign sda = sda_oe ? sda_out : 1'bz;

    always @(posedge clk or negedge rst_n) begin
        if (!rst_n) begin
            state      <= IDLE;
            bit_cnt    <= 4'd0;
            addr_shift <= 8'd0;
            data_shift <= 8'd0;
            div_cnt    <= 32'd0;
            phase      <= 1'b0;
            sda_out    <= 1'b0;
            sda_oe     <= 1'b0;
            scl        <= 1'b1;
            iic_done   <= 1'b0;
            ack_sample <= 1'b1;
        end else begin
            iic_done <= 1'b0;

            if (state == IDLE) begin
                div_cnt <= 32'd0;
            end else if (div_tick) begin
                div_cnt <= 32'd0;
            end else begin
                div_cnt <= div_cnt + 1'b1;
            end

            case (state)
                IDLE: begin
                    scl     <= 1'b1;
                    sda_out <= 1'b1;
                    sda_oe  <= 1'b0;
                    phase   <= 1'b0;
                    if (iic_start) begin
                        addr_shift <= dev_addr;
                        data_shift <= data;
                        state      <= START;
                    end
                end

                START: begin
                    if (div_tick) begin
                        if (!phase) begin
                            // START condition: SDA falls while SCL is high.
                            scl     <= 1'b1;
                            sda_out <= 1'b0;
                            sda_oe  <= 1'b1;
                            phase   <= 1'b1;
                        end else begin
                            scl     <= 1'b0;
                            bit_cnt <= 4'd7;
                            phase   <= 1'b0;
                            if (addr_shift[7]) begin
                                sda_out <= 1'b1;
                                sda_oe  <= 1'b0;
                            end else begin
                                sda_out <= 1'b0;
                                sda_oe  <= 1'b1;
                            end
                            state <= SEND_ADDR;
                        end
                    end
                end

                SEND_ADDR: begin
                    if (div_tick) begin
                        if (!scl) begin
                            scl <= 1'b1;
                        end else begin
                            scl <= 1'b0;
                            if (bit_cnt == 4'd0) begin
                                sda_out <= 1'b1;
                                sda_oe  <= 1'b0;
                                state   <= WAIT_ACK1;
                            end else begin
                                bit_cnt <= bit_cnt - 1'b1;
                                if (addr_shift[bit_cnt - 1'b1]) begin
                                    sda_out <= 1'b1;
                                    sda_oe  <= 1'b0;
                                end else begin
                                    sda_out <= 1'b0;
                                    sda_oe  <= 1'b1;
                                end
                            end
                        end
                    end
                end

                WAIT_ACK1: begin
                    if (div_tick) begin
                        if (!scl) begin
                            // Ninth SCL high level is the ACK sample point.
                            scl        <= 1'b1;
                            ack_sample <= sda;
                        end else begin
                            scl     <= 1'b0;
                            bit_cnt <= 4'd7;
                            if (data_shift[7]) begin
                                sda_out <= 1'b1;
                                sda_oe  <= 1'b0;
                            end else begin
                                sda_out <= 1'b0;
                                sda_oe  <= 1'b1;
                            end
                            state <= SEND_DATA;
                        end
                    end
                end

                SEND_DATA: begin
                    if (div_tick) begin
                        if (!scl) begin
                            scl <= 1'b1;
                        end else begin
                            scl <= 1'b0;
                            if (bit_cnt == 4'd0) begin
                                sda_out <= 1'b1;
                                sda_oe  <= 1'b0;
                                state   <= WAIT_ACK2;
                            end else begin
                                bit_cnt <= bit_cnt - 1'b1;
                                if (data_shift[bit_cnt - 1'b1]) begin
                                    sda_out <= 1'b1;
                                    sda_oe  <= 1'b0;
                                end else begin
                                    sda_out <= 1'b0;
                                    sda_oe  <= 1'b1;
                                end
                            end
                        end
                    end
                end

                WAIT_ACK2: begin
                    if (div_tick) begin
                        if (!scl) begin
                            scl        <= 1'b1;
                            ack_sample <= sda;
                        end else begin
                            scl     <= 1'b0;
                            sda_out <= 1'b0;
                            sda_oe  <= 1'b1;
                            phase   <= 1'b0;
                            state   <= STOP;
                        end
                    end
                end

                STOP: begin
                    if (div_tick) begin
                        if (!phase) begin
                            scl     <= 1'b1;
                            sda_out <= 1'b0;
                            sda_oe  <= 1'b1;
                            phase   <= 1'b1;
                        end else begin
                            // STOP condition: SDA rises while SCL is high.
                            scl      <= 1'b1;
                            sda_out  <= 1'b1;
                            sda_oe   <= 1'b0;
                            iic_done <= 1'b1;
                            phase    <= 1'b0;
                            state    <= IDLE;
                        end
                    end
                end

                default: begin
                    state <= IDLE;
                end
            endcase
        end
    end

endmodule

top_axi_iic_spi/top_axi_iic_spi.srcs/sim_1/new/tb_iic_master.v
`timescale 1ns / 1ps

module tb_iic_master;

    reg        clk = 1'b0;
    reg        rst_n = 1'b1;
    reg        iic_start = 1'b0;
    reg [7:0]  dev_addr = 8'h50;
    reg [7:0]  data = 8'ha5;
    wire       iic_done;
    wire       scl;
    wire       sda;

    reg        sda_ack_drive = 1'b0;
    reg [7:0]  rx_addr = 8'd0;
    reg [7:0]  rx_data = 8'd0;
    reg        rx_valid = 1'b0;
    integer    errors = 0;

    assign sda = sda_ack_drive ? 1'b0 : 1'bz;
    pullup(sda);

    iic_master #(
        .CLK_DIV(4)
    ) dut (
        .clk       (clk),
        .rst_n     (rst_n),
        .iic_start (iic_start),
        .dev_addr  (dev_addr),
        .data      (data),
        .iic_done  (iic_done),
        .scl       (scl),
        .sda       (sda)
    );

    initial forever #5 clk = ~clk;

    task fail;
        input [1023:0] msg;
        begin
            errors = errors + 1;
            $display("[%0t] FAIL: %0s", $time, msg);
        end
    endtask

    task recv_byte;
        output [7:0] value;
        integer bit_i;
        begin
            value = 8'd0;
            for (bit_i = 0; bit_i < 8; bit_i = bit_i + 1) begin
                @(posedge scl);
                #1;
                value = {value[6:0], sda};
            end
        end
    endtask

    task send_ack;
        begin
            @(negedge scl);
            sda_ack_drive = 1'b1;
            @(posedge scl);
            @(negedge scl);
            sda_ack_drive = 1'b0;
        end
    endtask

    initial begin
        forever begin
            @(negedge sda);
            if (scl) begin
                recv_byte(rx_addr);
                send_ack();
                recv_byte(rx_data);
                send_ack();
                wait (scl == 1'b1);
                @(posedge sda); // STOP condition: SDA rises while SCL is high.
                rx_valid = 1'b1;
            end
        end
    end

    initial begin
        $dumpfile("tb_iic_master.vcd");
        $dumpvars(0, tb_iic_master);

        errors = 0;
        rst_n = 1'b0; // Create a real negedge at time 0 for async reset.

        repeat (5) @(posedge clk);
        rst_n = 1'b1;
        repeat (2) @(posedge clk);

        @(negedge clk);
        iic_start = 1'b1;
        @(negedge clk);
        iic_start = 1'b0;

        wait (iic_done);
        repeat (2) @(posedge clk);
        if (!rx_valid)       fail("IIC slave model did not see STOP");
        if (rx_addr != 8'h50) fail("IIC address byte mismatch");
        if (rx_data != 8'ha5) fail("IIC data byte mismatch");
        if (scl != 1'b1)      fail("SCL did not return high after STOP");

        repeat (5) @(posedge clk);
        if (errors == 0) $display("[%0t] PASS: tb_iic_master", $time);
        else             $display("[%0t] FAIL: tb_iic_master found %0d error(s)", $time, errors);
        $finish;
    end

endmodule

top_axi_iic_spi/tb_iic_master.vcd
$date
	Fri May 29 09:29:29 2026
$end
$version
	Icarus Verilog
$end
$timescale
	1ps
$end
$scope module tb_iic_master $end
$var wire 1 ! sda $end
$var wire 1 " scl $end
$var wire 1 # iic_done $end
$var reg 1 $ clk $end
$var reg 8 % data [7:0] $end
$var reg 8 & dev_addr [7:0] $end
$var reg 1 ' iic_start $end
$var reg 1 ( rst_n $end
$var reg 8 ) rx_addr [7:0] $end
$var reg 8 * rx_data [7:0] $end
$var reg 1 + rx_valid $end
$var reg 1 , sda_ack_drive $end
$var integer 32 - errors [31:0] $end
$scope module dut $end
$var wire 1 $ clk $end
$var wire 8 . data [7:0] $end
$var wire 8 / dev_addr [7:0] $end
$var wire 1 ' iic_start $end
$var wire 1 ( rst_n $end
$var wire 1 ! sda $end
$var wire 1 0 div_tick $end
$var parameter 32 1 CLK_DIV $end
$var parameter 32 2 HALF_DIV $end
$var parameter 3 3 IDLE $end
$var parameter 3 4 SEND_ADDR $end
$var parameter 3 5 SEND_DATA $end
$var parameter 3 6 START $end
$var parameter 3 7 STOP $end
$var parameter 3 8 WAIT_ACK1 $end
$var parameter 3 9 WAIT_ACK2 $end
$var reg 1 : ack_sample $end
$var reg 8 ; addr_shift [7:0] $end
$var reg 4 < bit_cnt [3:0] $end
$var reg 8 = data_shift [7:0] $end
$var reg 32 > div_cnt [31:0] $end
$var reg 1 # iic_done $end
$var reg 1 ? phase $end
$var reg 1 " scl $end
$var reg 1 @ sda_oe $end
$var reg 1 A sda_out $end
$var reg 3 B state [2:0] $end
$upscope $end
$scope task fail $end
$var reg 1024 C msg [1023:0] $end
$upscope $end
$scope task recv_byte $end
$var reg 8 D value [7:0] $end
$var integer 32 E bit_i [31:0] $end
$upscope $end
$scope task send_ack $end
$upscope $end
$upscope $end
$enddefinitions $end
$comment Show the parameter values. $end
$dumpall
b101 9
b11 8
b110 7
b1 6
b100 5
b10 4
b0 3
b10 2
b100 1
$end
#0
$dumpvars
bx E
bx D
bx C
b0 B
0A
0@
0?
b0 >
b0 =
b0 <
b0 ;
1:
00
b1010000 /
b10100101 .
b0 -
0,
0+
b0 *
b0 )
0(
0'
b1010000 &
b10100101 %
0$
0#
1"
1!
$end
#5000
1$
#10000
0$
#15000
1$
#20000
0$
#25000
1$
#30000
0$
#35000
1$
#40000
0$
#45000
1A
1(
1$
#50000
0$
#55000
1$
#60000
0$
#65000
1$
#70000
1'
0$
#75000
b1 B
b10100101 =
b1010000 ;
1$
#80000
0'
0$
#85000
10
b1 >
1$
#90000
0$
#95000
b0 E
b0 D
0!
1?
1@
0A
00
b0 >
1$
#100000
0$
#105000
10
b1 >
1$
#110000
0$
#115000
b10 B
0?
b111 <
0"
00
b0 >
1$
#120000
0$
#125000
10
b1 >
1$
#130000
0$
#135000
1"
00
b0 >
1$
#136000
b1 E
#140000
0$
#145000
10
b1 >
1$
#150000
0$
#155000
1!
0@
1A
b110 <
0"
00
b0 >
1$
#160000
0$
#165000
10
b1 >
1$
#170000
0$
#175000
1"
00
b0 >
1$
#176000
b10 E
b1 D
#180000
0$
#185000
10
b1 >
1$
#190000
0$
#195000
0!
1@
0A
b101 <
0"
00
b0 >
1$
#200000
0$
#205000
10
b1 >
1$
#210000
0$
#215000
1"
00
b0 >
1$
#216000
b11 E
b10 D
#220000
0$
#225000
10
b1 >
1$
#230000
0$
#235000
1!
0@
1A
b100 <
0"
00
b0 >
1$
#240000
0$
#245000
10
b1 >
1$
#250000
0$
#255000
1"
00
b0 >
1$
#256000
b100 E
b101 D
#260000
0$
#265000
10
b1 >
1$
#270000
0$
#275000
0!
1@
0A
b11 <
0"
00
b0 >
1$
#280000
0$
#285000
10
b1 >
1$
#290000
0$
#295000
1"
00
b0 >
1$
#296000
b101 E
b1010 D
#300000
0$
#305000
10
b1 >
1$
#310000
0$
#315000
b10 <
0"
00
b0 >
1$
#320000
0$
#325000
10
b1 >
1$
#330000
0$
#335000
1"
00
b0 >
1$
#336000
b110 E
b10100 D
#340000
0$
#345000
10
b1 >
1$
#350000
0$
#355000
b1 <
0"
00
b0 >
1$
#360000
0$
#365000
10
b1 >
1$
#370000
0$
#375000
1"
00
b0 >
1$
#376000
b111 E
b101000 D
#380000
0$
#385000
10
b1 >
1$
#390000
0$
#395000
b0 <
0"
00
b0 >
1$
#400000
0$
#405000
10
b1 >
1$
#410000
0$
#415000
1"
00
b0 >
1$
#416000
b1010000 )
b1000 E
b1010000 D
#420000
0$
#425000
10
b1 >
1$
#430000
0$
#435000
0!
1,
b11 B
0@
1A
0"
00
b0 >
1$
#440000
0$
#445000
10
b1 >
1$
#450000
0$
#455000
0:
1"
00
b0 >
1$
#460000
0$
#465000
10
b1 >
1$
#470000
0$
#475000
1!
b0 E
b0 D
0,
b100 B
b111 <
0"
00
b0 >
1$
#480000
0$
#485000
10
b1 >
1$
#490000
0$
#495000
1"
00
b0 >
1$
#496000
b1 E
b1 D
#500000
0$
#505000
10
b1 >
1$
#510000
0$
#515000
0!
1@
0A
b110 <
0"
00
b0 >
1$
#520000
0$
#525000
10
b1 >
1$
#530000
0$
#535000
1"
00
b0 >
1$
#536000
b10 E
b10 D
#540000
0$
#545000
10
b1 >
1$
#550000
0$
#555000
1!
0@
1A
b101 <
0"
00
b0 >
1$
#560000
0$
#565000
10
b1 >
1$
#570000
0$
#575000
1"
00
b0 >
1$
#576000
b11 E
b101 D
#580000
0$
#585000
10
b1 >
1$
#590000
0$
#595000
0!
1@
0A
b100 <
0"
00
b0 >
1$
#600000
0$
#605000
10
b1 >
1$
#610000
0$
#615000
1"
00
b0 >
1$
#616000
b100 E
b1010 D
#620000
0$
#625000
10
b1 >
1$
#630000
0$
#635000
b11 <
0"
00
b0 >
1$
#640000
0$
#645000
10
b1 >
1$
#650000
0$
#655000
1"
00
b0 >
1$
#656000
b101 E
b10100 D
#660000
0$
#665000
10
b1 >
1$
#670000
0$
#675000
1!
0@
1A
b10 <
0"
00
b0 >
1$
#680000
0$
#685000
10
b1 >
1$
#690000
0$
#695000
1"
00
b0 >
1$
#696000
b110 E
b101001 D
#700000
0$
#705000
10
b1 >
1$
#710000
0$
#715000
0!
1@
0A
b1 <
0"
00
b0 >
1$
#720000
0$
#725000
10
b1 >
1$
#730000
0$
#735000
1"
00
b0 >
1$
#736000
b111 E
b1010010 D
#740000
0$
#745000
10
b1 >
1$
#750000
0$
#755000
1!
0@
1A
b0 <
0"
00
b0 >
1$
#760000
0$
#765000
10
b1 >
1$
#770000
0$
#775000
1"
00
b0 >
1$
#776000
b10100101 *
b1000 E
b10100101 D
#780000
0$
#785000
10
b1 >
1$
#790000
0$
#795000
0!
1,
b101 B
0"
00
b0 >
1$
#800000
0$
#805000
10
b1 >
1$
#810000
0$
#815000
1"
00
b0 >
1$
#820000
0$
#825000
10
b1 >
1$
#830000
0$
#835000
0,
b110 B
1@
0A
0"
00
b0 >
1$
#840000
0$
#845000
10
b1 >
1$
#850000
0$
#855000
1?
1"
00
b0 >
1$
#860000
0$
#865000
10
b1 >
1$
#870000
0$
#875000
1+
1!
b0 B
0?
1#
0@
1A
00
b0 >
1$
#880000
0$
#885000
0#
1$
