top_axi_iic_spi/top_axi_iic_spi.srcs/sources_1/new/spi_master.v
`timescale 1ns / 1ps

module spi_master #(
    parameter integer CLK_DIV = 10
    )(
    input  wire       clk,
    input  wire       rst_n,
    input  wire       spi_start,
    input  wire [7:0] data_in,
    output reg        spi_done,
    output reg        sck,
    output reg        mosi,
    output reg        cs
    );

    localparam integer HALF_DIV = (CLK_DIV <= 2) ? 1 : (CLK_DIV / 2);

    localparam IDLE = 2'd0;
    localparam SEND = 2'd1;
    localparam DONE = 2'd2;

    reg [1:0]  state;
    reg [2:0]  bit_cnt;
    reg [7:0]  shift_reg;
    reg [31:0] div_cnt;

    wire div_tick = (div_cnt == (HALF_DIV - 1));

    always @(posedge clk or negedge rst_n) begin
        if (!rst_n) begin
            state     <= IDLE;
            bit_cnt   <= 3'd0;
            shift_reg <= 8'd0;
            div_cnt   <= 32'd0;
            spi_done  <= 1'b0;
            sck       <= 1'b0;
            mosi      <= 1'b0;
            cs        <= 1'b1;
        end else begin
            spi_done <= 1'b0;

            if (state == SEND) begin
                if (div_tick) begin
                    div_cnt <= 32'd0;
                end else begin
                    div_cnt <= div_cnt + 1'b1;
                end
            end else begin
                div_cnt <= 32'd0;
            end

            case (state)
                IDLE: begin
                    sck <= 1'b0;  // SPI mode 0: CPOL=0, idle clock is low.
                    cs  <= 1'b1;
                    if (spi_start) begin
                        shift_reg <= data_in;
                        mosi      <= data_in[7]; // CPHA=0: first bit is stable before first rising edge.
                        bit_cnt   <= 3'd0;
                        cs        <= 1'b0;
                        state     <= SEND;
                    end
                end

                SEND: begin
                    if (div_tick) begin
                        if (!sck) begin
                            sck <= 1'b1; // Slave samples MOSI on this rising edge.
                        end else begin
                            sck <= 1'b0; // Master changes MOSI on the falling edge.
                            if (bit_cnt == 3'd7) begin
                                cs    <= 1'b1;
                                mosi  <= 1'b0;
                                state <= DONE;
                            end else begin
                                bit_cnt   <= bit_cnt + 1'b1;
                                shift_reg <= {shift_reg[6:0], 1'b0};
                                mosi      <= shift_reg[6];
                            end
                        end
                    end
                end

                DONE: begin
                    spi_done <= 1'b1;
                    state    <= IDLE;
                end

                default: begin
                    state <= IDLE;
                end
            endcase
        end
    end

endmodule

top_axi_iic_spi/top_axi_iic_spi.srcs/sim_1/new/tb_spi_master.v
`timescale 1ns / 1ps

module tb_spi_master;

    reg        clk = 1'b0;
    reg        rst_n = 1'b1;
    reg        spi_start = 1'b0;
    reg [7:0]  data_in = 8'h5c;
    wire       spi_done;
    wire       sck;
    wire       mosi;
    wire       cs;

    reg [7:0]  rx_shift = 8'd0;
    reg [7:0]  rx_data = 8'd0;
    reg        rx_valid = 1'b0;
    integer    errors = 0;
    integer    bit_i = 0;

    spi_master #(
        .CLK_DIV(4)
    ) dut (
        .clk       (clk),
        .rst_n     (rst_n),
        .spi_start (spi_start),
        .data_in   (data_in),
        .spi_done  (spi_done),
        .sck       (sck),
        .mosi      (mosi),
        .cs        (cs)
    );

    initial forever #5 clk = ~clk;

    task fail;
        input [1023:0] msg;
        begin
            errors = errors + 1;
            $display("[%0t] FAIL: %0s", $time, msg);
        end
    endtask

    initial begin
        forever begin
            @(negedge cs);
            rx_shift = 8'd0;
            rx_valid = 1'b0;
            for (bit_i = 0; bit_i < 8; bit_i = bit_i + 1) begin
                @(posedge sck);
                #1;
                rx_shift = {rx_shift[6:0], mosi}; // SPI mode 0 samples on rising SCK.
            end
            @(posedge cs);
            rx_data  = rx_shift;
            rx_valid = 1'b1;
        end
    end

    initial begin
        $dumpfile("tb_spi_master.vcd");
        $dumpvars(0, tb_spi_master);

        errors = 0;
        rst_n = 1'b0; // Create a real negedge at time 0 for async reset.

        repeat (5) @(posedge clk);
        rst_n = 1'b1;
        repeat (2) @(posedge clk);

        @(negedge clk);
        spi_start = 1'b1;
        @(negedge clk);
        spi_start = 1'b0;

        wait (spi_done);
        repeat (2) @(posedge clk);
        if (!rx_valid)       fail("SPI slave model did not receive a byte");
        if (rx_data != 8'h5c) fail("SPI received data mismatch");
        if (cs != 1'b1)       fail("CS did not return high");
        if (sck != 1'b0)      fail("SCK did not return to mode-0 idle low");

        repeat (5) @(posedge clk);
        if (errors == 0) $display("[%0t] PASS: tb_spi_master", $time);
        else             $display("[%0t] FAIL: tb_spi_master found %0d error(s)", $time, errors);
        $finish;
    end

endmodule

top_axi_iic_spi/tb_spi_master.vcd
$date
	Fri May 29 09:29:29 2026
$end
$version
	Icarus Verilog
$end
$timescale
	1ps
$end
$scope module tb_spi_master $end
$var wire 1 ! spi_done $end
$var wire 1 " sck $end
$var wire 1 # mosi $end
$var wire 1 $ cs $end
$var reg 1 % clk $end
$var reg 8 & data_in [7:0] $end
$var reg 1 ' rst_n $end
$var reg 8 ( rx_data [7:0] $end
$var reg 8 ) rx_shift [7:0] $end
$var reg 1 * rx_valid $end
$var reg 1 + spi_start $end
$var integer 32 , bit_i [31:0] $end
$var integer 32 - errors [31:0] $end
$scope module dut $end
$var wire 1 % clk $end
$var wire 8 . data_in [7:0] $end
$var wire 1 ' rst_n $end
$var wire 1 + spi_start $end
$var wire 1 / div_tick $end
$var parameter 32 0 CLK_DIV $end
$var parameter 2 1 DONE $end
$var parameter 32 2 HALF_DIV $end
$var parameter 2 3 IDLE $end
$var parameter 2 4 SEND $end
$var reg 3 5 bit_cnt [2:0] $end
$var reg 1 $ cs $end
$var reg 32 6 div_cnt [31:0] $end
$var reg 1 # mosi $end
$var reg 1 " sck $end
$var reg 8 7 shift_reg [7:0] $end
$var reg 1 ! spi_done $end
$var reg 2 8 state [1:0] $end
$upscope $end
$scope task fail $end
$var reg 1024 9 msg [1023:0] $end
$upscope $end
$upscope $end
$enddefinitions $end
$comment Show the parameter values. $end
$dumpall
b1 4
b0 3
b10 2
b10 1
b100 0
$end
#0
$dumpvars
bx 9
b0 8
b0 7
b0 6
b0 5
0/
b1011100 .
b0 -
b0 ,
0+
0*
b0 )
b0 (
0'
b1011100 &
0%
1$
0#
0"
0!
$end
#5000
1%
#10000
0%
#15000
1%
#20000
0%
#25000
1%
#30000
0%
#35000
1%
#40000
0%
#45000
1'
1%
#50000
0%
#55000
1%
#60000
0%
#65000
1%
#70000
1+
0%
#75000
b1 8
0$
b1011100 7
1%
#80000
0+
0%
#85000
1/
b1 6
1%
#90000
0%
#95000
1"
0/
b0 6
1%
#96000
b1 ,
#100000
0%
#105000
1/
b1 6
1%
#110000
0%
#115000
1#
b10111000 7
b1 5
0"
0/
b0 6
1%
#120000
0%
#125000
1/
b1 6
1%
#130000
0%
#135000
1"
0/
b0 6
1%
#136000
b10 ,
b1 )
#140000
0%
#145000
1/
b1 6
1%
#150000
0%
#155000
0#
b1110000 7
b10 5
0"
0/
b0 6
1%
#160000
0%
#165000
1/
b1 6
1%
#170000
0%
#175000
1"
0/
b0 6
1%
#176000
b11 ,
b10 )
#180000
0%
#185000
1/
b1 6
1%
#190000
0%
#195000
1#
b11100000 7
b11 5
0"
0/
b0 6
1%
#200000
0%
#205000
1/
b1 6
1%
#210000
0%
#215000
1"
0/
b0 6
1%
#216000
b100 ,
b101 )
#220000
0%
#225000
1/
b1 6
1%
#230000
0%
#235000
b11000000 7
b100 5
0"
0/
b0 6
1%
#240000
0%
#245000
1/
b1 6
1%
#250000
0%
#255000
1"
0/
b0 6
1%
#256000
b101 ,
b1011 )
#260000
0%
#265000
1/
b1 6
1%
#270000
0%
#275000
b10000000 7
b101 5
0"
0/
b0 6
1%
#280000
0%
#285000
1/
b1 6
1%
#290000
0%
#295000
1"
0/
b0 6
1%
#296000
b110 ,
b10111 )
#300000
0%
#305000
1/
b1 6
1%
#310000
0%
#315000
0#
b0 7
b110 5
0"
0/
b0 6
1%
#320000
0%
#325000
1/
b1 6
1%
#330000
0%
#335000
1"
0/
b0 6
1%
#336000
b111 ,
b101110 )
#340000
0%
#345000
1/
b1 6
1%
#350000
0%
#355000
b111 5
0"
0/
b0 6
1%
#360000
0%
#365000
1/
b1 6
1%
#370000
0%
#375000
1"
0/
b0 6
1%
#376000
b1000 ,
b1011100 )
#380000
0%
#385000
1/
b1 6
1%
#390000
0%
#395000
1*
b1011100 (
b10 8
1$
0"
0/
b0 6
1%
#400000
0%
#405000
b0 8
1!
1%
#410000
0%
#415000
0!
1%
